LAMP/DAQ.py
LAMP/__init__.py
LAMP/diagnostic.py
LAMP/experiment.py
LAMP/meta.py
LAMP/results.py
LAMP/DAQs/Apollo.py
LAMP/DAQs/GeminiMirage.py
LAMP/DAQs/NoDAQ.py
LAMP/diagnostics/Camera.py
LAMP/diagnostics/ESpec.py
LAMP/diagnostics/FocalSpot.py
LAMP/metas/ApolloDB.py
LAMP/metas/GoogleSheetOffline.py
LAMP/utils/general.py
LAMP/utils/image_proc.py
LAMP/utils/io.py
LAMP/utils/plotting.py
LAMP/utils/xrays/calc_bragg_dispersion.py
LAMP/utils/xrays/filter_transmission.py
LAMP/utils/xrays/pyNIST.py
lamp_api-0.1.0.dist-info/licenses/LICENSE
lamp_api-0.1.0.dist-info/METADATA
lamp_api-0.1.0.dist-info/WHEEL
lamp_api-0.1.0.dist-info/top_level.txt
lamp_api-0.1.0.dist-info/RECORD
